moondream_cuda/__init__.py
moondream_cuda-0.1.0.dist-info/METADATA
moondream_cuda-0.1.0.dist-info/WHEEL
moondream_cuda-0.1.0.dist-info/RECORD
