Metadata-Version: 2.1
Name: moondream-cuda
Version: 0.1.0
Summary: 
Author: Vik Korrapati
Author-email: vikhyatk@gmail.com
Requires-Python: >=3.10,<4.0
Classifier: Programming Language :: Python :: 3
Classifier: Programming Language :: Python :: 3.10
Classifier: Programming Language :: Python :: 3.11
Classifier: Programming Language :: Python :: 3.12
Classifier: Programming Language :: Python :: 3.13
Requires-Dist: onnxruntime-gpu (>=1.20.0,<2.0.0)
